codeset/__init__.py
codeset/_base_client.py
codeset/_client.py
codeset/_compat.py
codeset/_constants.py
codeset/_exceptions.py
codeset/_files.py
codeset/_models.py
codeset/_qs.py
codeset/_resource.py
codeset/_response.py
codeset/_streaming.py
codeset/_types.py
codeset/_version.py
codeset/py.typed
codeset/_utils/__init__.py
codeset/_utils/_compat.py
codeset/_utils/_datetime_parse.py
codeset/_utils/_logs.py
codeset/_utils/_proxy.py
codeset/_utils/_reflection.py
codeset/_utils/_resources_proxy.py
codeset/_utils/_streams.py
codeset/_utils/_sync.py
codeset/_utils/_transform.py
codeset/_utils/_typing.py
codeset/_utils/_utils.py
codeset/lib/.keep
codeset/resources/__init__.py
codeset/resources/datasets.py
codeset/resources/health.py
codeset/resources/samples.py
codeset/resources/sessions/__init__.py
codeset/resources/sessions/sessions.py
codeset/resources/sessions/verify.py
codeset/types/__init__.py
codeset/types/container_info.py
codeset/types/dataset_list_response.py
codeset/types/error_info.py
codeset/types/health_check_response.py
codeset/types/interaction.py
codeset/types/interaction_status.py
codeset/types/sample_download_params.py
codeset/types/sample_list_params.py
codeset/types/sample_list_response.py
codeset/types/session.py
codeset/types/session_close_response.py
codeset/types/session_create_params.py
codeset/types/session_create_response.py
codeset/types/session_execute_command_params.py
codeset/types/session_execute_command_response.py
codeset/types/session_list_response.py
codeset/types/session_status.py
codeset/types/session_str_replace_params.py
codeset/types/session_str_replace_response.py
codeset/types/sessions/__init__.py
codeset/types/sessions/job_status.py
codeset/types/sessions/verify_start_response.py
codeset/types/sessions/verify_status_response.py
codeset-0.8.1.dist-info/METADATA
codeset-0.8.1.dist-info/WHEEL
codeset-0.8.1.dist-info/licenses/LICENSE
codeset-0.8.1.dist-info/RECORD
